{
  "$schema": "../gen/schemas/desktop-schema.json",
  "identifier": "main",
  "description": "Capability for the main window",
  "windows": [
    "main"
  ],
  "permissions": [
    "core:default",
    "shell:default",
    "fs:default",
    "dialog:default",
    "fs:allow-read-file",
    "fs:allow-read-text-file",
    "fs:allow-write-file",
    "fs:allow-write-text-file",
    "fs:allow-mkdir",
    "fs:allow-exists",
    "fs:allow-watch",
    "fs:allow-unwatch",
    "shell:allow-open",
    "dialog:allow-open",
    "dialog:allow-save"
  ],
  "platforms": [
    "linux",
    "macOS",
    "windows"
  ]
}